pycollect/__init__.py
pycollect/module_finder.py
pycollect/python_file_collector.py
pycollect-0.2.3.dist-info/AUTHORS.rst
pycollect-0.2.3.dist-info/LICENSE
pycollect-0.2.3.dist-info/METADATA
pycollect-0.2.3.dist-info/WHEEL
pycollect-0.2.3.dist-info/top_level.txt
pycollect-0.2.3.dist-info/RECORD
