Metadata-Version: 2.1
Name: pycollect
Version: 0.2.3
Summary: Utility library to collect files recursively
Home-page: https://github.com/allrod5/pycollect
Author: Rodrigo Martins de Oliveira
Author-email: allrod5@hotmail.com
License: MIT license
Project-URL: Documentation, https://allrod5.github.io/pycollect/
Project-URL: Changelog, https://allrod5.github.io/pycollect/en/latest/changelog.html
Project-URL: Issue Tracker, https://github.com/allrod5/pycollect/issues
Keywords: file,py,traversal,directory
Platform: UNKNOWN
Classifier: Development Status :: 5 - Production/Stable
Classifier: Intended Audience :: Developers
Classifier: License :: OSI Approved :: MIT License
Classifier: Operating System :: Unix
Classifier: Operating System :: POSIX
Classifier: Operating System :: Microsoft :: Windows
Classifier: Programming Language :: Python
Classifier: Programming Language :: Python :: 3.6
Classifier: Programming Language :: Python :: 3.7
Classifier: Programming Language :: Python :: 3.8
Classifier: Programming Language :: Python :: Implementation :: CPython
Classifier: Programming Language :: Python :: Implementation :: PyPy
Classifier: Topic :: Utilities
Requires-Python: >=3.6
